Metadata-Version: 2.2
Name: iitypes
Version: 0.0.2
Summary: Actian Ingres/Vector data types package
Author: Roy Hann
Author-email: roy.hann@rationalcommerce.com
License: MIT
Keywords: Ingres,Actian
License-File: LICENSE
Requires-Dist: loguru>=0.5.3
Requires-Dist: pyngres>=0.1.0
Requires-Dist: multipledispatch>=1.0.0
